LICENSE
MANIFEST.in
README.md
setup.cfg
setup.py
bergholm/__init__.py
bergholm/api.py
bergholm/expections.py
bergholm_api_client.egg-info/PKG-INFO
bergholm_api_client.egg-info/SOURCES.txt
bergholm_api_client.egg-info/dependency_links.txt
bergholm_api_client.egg-info/not-zip-safe
bergholm_api_client.egg-info/requires.txt
bergholm_api_client.egg-info/top_level.txt