Metadata-Version: 1.0
Name: bergholm-api-client
Version: 0.0.3
Summary: Simple Client to fetch products from http://www.bergholm.com/
Home-page: https://github.com/iktw/bergholm-api-client
Author: Mohammed Hammoud
Author-email: mohammed@iktw.se
License: MIT licence, see LICENSE
Platform: UNKNOWN
